{"name":"Sdanielf.GitHub.io","tagline":"Sitio web personal","body":"### Materiales\r\n\r\n* [Diapositivas de talleres anteriores](http://sdanielf.github.io/workshops/)\r\n\r\n### Sobre el autor\r\nComencé a programar a los 12 años. Actualmente soy desarrollador de software y estudiante. Desde hace dos años enseño programación voluntariamente a personas de diferentes niveles. Hago talleres con jóvenes de 12 años que comienzan a programar y con estudiantes de bachillerato en informática. Eventualmente respondo consultas de estudiantes universitarios y desarrolladores profesionales.\r\n","google":"","note":"Don't delete this file! It's used internally to help with page regeneration."}